pytest_httpchain_userfunc/__init__.py
pytest_httpchain_userfunc/exceptions.py
pytest_httpchain_userfunc/userfunc.py
pytest_httpchain_userfunc-0.2.1.dist-info/WHEEL
pytest_httpchain_userfunc-0.2.1.dist-info/METADATA
pytest_httpchain_userfunc-0.2.1.dist-info/RECORD
