Metadata-Version: 2.3
Name: pytest-httpchain-userfunc
Version: 0.2.1
Summary: User functions support for pytest-httpchain
Author: Alexander Eresov
Author-email: Alexander Eresov <aeresov@gmail.com>
Requires-Python: >=3.13
